{
  "original_sample": 8236,
  "final_sample": 5735,
  "excluded_cases": 2501,
  "retention_rate": 69.63331714424477,
  "missing_pattern": {
    "Missing_Count": {
      "k19_somente_medida": 2391,
      "k18_somente": 2379,
      "k16_liquido": 2379,
      "k15_recebeu": 2379,
      "k13_tempo_medida": 2379,
      "k12_tempo": 2379,
      "k04_prenatal_semanas": 2226,
      "k05_prenatal_consultas": 2226,
      "k06_peso_engravidar": 2108,
      "k07_peso_final": 2106,
      "k08_quilos": 2104,
      "t06_altura_medida2": 486,
      "t05_altura_medida1": 485,
      "bb04_idade_da_mae": 7,
      "vd_zimc": 4,
      "b02_sexo": 0,
      "j03_cor": 0,
      "h04_parto": 0,
      "h03_altura": 0,
      "h02_peso": 0,
      "h01_semanas_gravidez": 0,
      "d01_cor": 0,
      "b04_idade": 0,
      "id_anon": 0
    },
    "Missing_Percentage": {
      "k19_somente_medida": 29.03,
      "k18_somente": 28.89,
      "k16_liquido": 28.89,
      "k15_recebeu": 28.89,
      "k13_tempo_medida": 28.89,
      "k12_tempo": 28.89,
      "k04_prenatal_semanas": 27.03,
      "k05_prenatal_consultas": 27.03,
      "k06_peso_engravidar": 25.59,
      "k07_peso_final": 25.57,
      "k08_quilos": 25.55,
      "t06_altura_medida2": 5.9,
      "t05_altura_medida1": 5.89,
      "bb04_idade_da_mae": 0.08,
      "vd_zimc": 0.05,
      "b02_sexo": 0.0,
      "j03_cor": 0.0,
      "h04_parto": 0.0,
      "h03_altura": 0.0,
      "h02_peso": 0.0,
      "h01_semanas_gravidez": 0.0,
      "d01_cor": 0.0,
      "b04_idade": 0.0,
      "id_anon": 0.0
    }
  }
}